ddsl_wg/__init__.py
ddsl_wg/timer.py
ddsl_wg/wg.py
ddsl_wg-0.1.10.dist-info/LICENSE
ddsl_wg-0.1.10.dist-info/METADATA
ddsl_wg-0.1.10.dist-info/WHEEL
ddsl_wg-0.1.10.dist-info/top_level.txt
ddsl_wg-0.1.10.dist-info/RECORD
