Metadata-Version: 2.1
Name: ddsl-wg
Version: 0.1.10
Summary: A workload generator made in DDSL lab of University of Alberta.
Home-page: https://github.com/nimamahmoudi/ddsl_wg
Author: Nima Mahmoudi
Author-email: nima_mahmoudi@live.com
License: UNKNOWN
Platform: UNKNOWN
Classifier: Development Status :: 4 - Beta
Classifier: Programming Language :: Python
Classifier: Programming Language :: Python :: 3
Classifier: Programming Language :: Python :: 3.6
Classifier: Intended Audience :: Developers
Classifier: License :: OSI Approved :: MIT License
Classifier: Operating System :: OS Independent
Requires-Dist: numpy (>=1.16.4)
Requires-Dist: boto3 (>=1.9.170)
Requires-Dist: pandas (>=0.24.2)
